[
    {
        "id": 1,
        "question": "Hvem i rommet ville du sveipet ja til på tinder?",
        "rule": "Perfekt for å starte jentevorset med god selvtillit. Husk å inkluder alle!"
    },
    {
        "id": 2,
        "question": "Hvem i rommet skulle du helst ønske var singel?"
    },
    {
        "id": 3,
        "question": "Hvem har de fineste øynene?"
    },
    {
        "id": 4,
        "question": "Hvem digger du mest i rommet?"
    },
    {
        "id": 5,
        "question": "Hvem kunne aldri vært utro?"
    },
    {
        "id": 6,
        "question": "Hvem i rommet ville du pult?"
    },
    {
        "id": 7,
        "question": "Hvem har best outfit i kveld?"
    },
    {
        "id": 8,
        "question": "Hvem er mest morsom?"
    },
    {
        "id": 9,
        "question": "Alle drikker"
    },
    {
        "id": 10,
        "question": "Hvem lukter best?"
    },
    {
        "id": 11,
        "question": "Hvem har det fineste smilet?"
    },
    {
        "id": 12,
        "question": "Hvem ser mest clean ut? (clean vs musty)"
    },
    {
        "id": 13,
        "question": "Hvem har sommerkroppen klar?"
    },
    {
        "id": 14,
        "question": "Hvem har den beste personligheten?"
    },
    {
        "id": 15,
        "question": "SKÅL!!!"
    },
    {
        "id": 16,
        "question": "Hvem blir mest likt av nye personer?"
    },
    {
        "id": 17,
        "question": "Hvem er mest populær?"
    },
    {
        "id": 18,
        "question": "Hvem hadde vært en kjendis alle hadde likt?"
    },
    {
        "id": 19,
        "question": "Hvem hadde tatt seg best ut på reality tv?"
    },
    {
        "id": 20,
        "question": "Hvem er svigemors/svigefars drøm?"
    },
    {
        "id": 21,
        "question": "Hvem har den beste stilen?"
    },
    {
        "id": 22,
        "question": "Hvem er mest fotogen?"
    },
    {
        "id": 23,
        "question": "Hvem sminker seg best?"
    },
    {
        "id": 24,
        "question": "Hvem har den beste musikksmaken?"
    },
    {
        "id": 25,
        "question": "Hvem kunne vunnet Miss Norway?"
    },
    {
        "id": 26,
        "question": "Hvem har de diggeste foreldrene?"
    },
    {
        "id": 27,
        "question": "Hvem ville vært den største milfen?"
    },
    {
        "id": 28,
        "question": "Hvem ville vært beste kjæresten?"
    },
    {
        "id": 29,
        "question": "Hvem ville vært den exen man skulle ønske kom hvis man var med på ex?"
    }
]
